gitscripts/__init__.py
gitscripts/git_ver.py
gitscripts/python_ver.py
gitscripts/rust_ver.py
gitscripts/scripts/__init__.py
gitscripts/scripts/python_ver.py
gitscripts/scripts/rust_ver.py
gitscripts/tools/__init__.py
gitscripts/tools/filesystem.py
gitscripts/tools/git.py
gitscripts/tools/git_ops.py
gitscripts/tools/logging_.py
gitscripts/tools/setup_.py
gitscripts/tools/setup_utils.py
gitscripts/tools/str_utils.py
gitscripts/version_increment/__init__.py
gitscripts/version_increment/python/__init__.py
gitscripts/version_increment/python/lang_utils.py
gitscripts/version_increment/python/python.py
gitscripts/version_increment/rust/__init__.py
gitscripts/version_increment/rust/general_utils.py
gitscripts/version_increment/rust/lang_utils.py
gitscripts/version_increment/rust/rust.py
gitscripts/version_increment/rust/rustlang_utils.py
gitscripts/version_increment/tools/__init__.py
gitscripts/version_increment/tools/lang_utils.py
gitscripts/version_increment/tools/parsing.py
gitscripts/version_increment/tools/parsing_utils.py
gitscripts/version_increment/tools/types_.py
tests/__init__.py
git_scripts-2.0.0.dist-info/LICENSE
git_scripts-2.0.0.dist-info/METADATA
git_scripts-2.0.0.dist-info/WHEEL
git_scripts-2.0.0.dist-info/top_level.txt
git_scripts-2.0.0.dist-info/RECORD
