Metadata-Version: 2.1
Name: git-scripts
Version: 2.0.0
Summary: Provides scripts useful for extending the functionality of git commands
Home-page: https://github.com/Grimmslaw/git-scripts.git
Author: Wes Rickey
Author-email: d.wrickey@gmail.com
License: UNKNOWN
Platform: UNKNOWN
Classifier: Programming Language :: Python :: 3
Classifier: License :: OSI Approved :: GNU General Public License v3 (GPLv3)
Classifier: Operating System :: OS Independent
Requires-Python: >=3.6
